pymkup/__init__.py
pymkup/column_data.py
pymkup/data_conversion.py
pymkup/pymkup.py
pymkup-0.7.dist-info/LICENSE.txt
pymkup-0.7.dist-info/METADATA
pymkup-0.7.dist-info/WHEEL
pymkup-0.7.dist-info/top_level.txt
pymkup-0.7.dist-info/RECORD
