Metadata-Version: 2.1
Name: pymkup
Version: 0.7
Summary: Accessing Bluebeam Revu PDF Data
Home-page: https://github.com/psolin/pymkup
Author: Paul Solin
Author-email: paulsolin@gmail.com
License: MIT
Platform: UNKNOWN
Classifier: License :: OSI Approved :: MIT License
Classifier: Programming Language :: Python :: 3
Classifier: Programming Language :: Python :: 3.7
Requires-Dist: pdfreader
Requires-Dist: matplotlib
